birdhouse_birdy-0.9.1.dist-info/licenses/AUTHORS.rst
birdhouse_birdy-0.9.1.dist-info/licenses/LICENSE.txt
birdy/__init__.py
birdy/dependencies.py
birdy/exceptions.py
birdy/utils.py
birdy/cli/__init__.py
birdy/cli/base.py
birdy/cli/misc.py
birdy/cli/run.py
birdy/cli/types.py
birdy/client/__init__.py
birdy/client/base.py
birdy/client/converters.py
birdy/client/notebook.py
birdy/client/outputs.py
birdy/client/utils.py
birdy/ipyleafletwfs/README.md
birdy/ipyleafletwfs/__init__.py
birdy/ipyleafletwfs/base.py
birdy/ipyleafletwfs/examples/ipyleafletwfs_guide.ipynb
birdy/ipyleafletwfs/examples/quickstart-template.ipynb
birdy/ipyleafletwfs/examples/wfs_constructor.ipynb
birdy/templates/cmd.py.j2
birdhouse_birdy-0.9.1.dist-info/METADATA
birdhouse_birdy-0.9.1.dist-info/WHEEL
birdhouse_birdy-0.9.1.dist-info/entry_points.txt
birdhouse_birdy-0.9.1.dist-info/top_level.txt
birdhouse_birdy-0.9.1.dist-info/RECORD
