Metadata-Version: 2.4
Name: birdhouse-birdy
Version: 0.9.1
Summary: Birdy provides a command-line tool to work with Web Processing Services.
Home-page: https://github.com/bird-house/birdy
Author: Carsten Ehbrecht
Author-email: ehbrecht@dkrz.de
License: Apache License v2.0
Keywords: wps pywps owslib geopython birdy birdhouse
Classifier: Development Status :: 4 - Beta
Classifier: Intended Audience :: Science/Research
Classifier: Operating System :: MacOS :: MacOS X
Classifier: Operating System :: Microsoft :: Windows
Classifier: Operating System :: POSIX
Classifier: Programming Language :: Python
Classifier: Programming Language :: Python :: 3
Classifier: Programming Language :: Python :: 3.9
Classifier: Programming Language :: Python :: 3.10
Classifier: Programming Language :: Python :: 3.11
Classifier: Programming Language :: Python :: 3.12
Classifier: Programming Language :: Python :: 3.13
Classifier: Topic :: Scientific/Engineering :: Atmospheric Science
Requires-Python: >=3.9.0
License-File: LICENSE.txt
License-File: AUTHORS.rst
Requires-Dist: boltons>=23.0
Requires-Dist: click>=8.1.0
Requires-Dist: jinja2>=3.0.0
Requires-Dist: lxml>=5.0.0
Requires-Dist: owslib>=0.19.2
Requires-Dist: packaging>=23.0
Requires-Dist: pyOpenSSL>=23.0
Requires-Dist: python-dateutil>=2.8.1
Requires-Dist: requests>=2.24.0
Requires-Dist: urllib3>=2.0.2
Requires-Dist: wrapt>=1.14.0
Provides-Extra: dev
Requires-Dist: black>=24.2.0; extra == "dev"
Requires-Dist: build>=1.0; extra == "dev"
Requires-Dist: bump-my-version>=1.0.0; extra == "dev"
Requires-Dist: coverage>=7.5.0; extra == "dev"
Requires-Dist: flake8>=7.0; extra == "dev"
Requires-Dist: ipykernel>=6.25.0; extra == "dev"
Requires-Dist: nbconvert>=7.3.0; extra == "dev"
Requires-Dist: nbsphinx>=0.9.5; extra == "dev"
Requires-Dist: nbval>=0.9.6; extra == "dev"
Requires-Dist: pip>=23.3; extra == "dev"
Requires-Dist: pre-commit>=3.6.2; extra == "dev"
Requires-Dist: pytest>=8.0.0; extra == "dev"
Requires-Dist: pytest-notebook>=0.6.0; extra == "dev"
Requires-Dist: sphinx-codeautolink; extra == "dev"
Requires-Dist: sphinx-copybutton; extra == "dev"
Requires-Dist: sphinx<8.2.0,>=7.0.0; extra == "dev"
Requires-Dist: twine>=4.0.0; extra == "dev"
Requires-Dist: watchdog>=4.0.0; extra == "dev"
Provides-Extra: docs
Requires-Dist: ipython!=9.0.0,>8.5.0; extra == "docs"
Requires-Dist: nbsphinx>=0.9.5; extra == "docs"
Requires-Dist: sphinx<8.2.0,>=7.0.0; extra == "docs"
Requires-Dist: sphinx-codeautolink>=0.16.0; extra == "docs"
Requires-Dist: sphinx-copybutton; extra == "docs"
Provides-Extra: extra
Requires-Dist: fiona>=1.9.0; extra == "extra"
Requires-Dist: geojson>=3.0.0; extra == "extra"
Requires-Dist: ipyleaflet>=0.18.0; extra == "extra"
Requires-Dist: ipython!=9.0.0,>8.5.0; extra == "extra"
Requires-Dist: ipywidgets>=8.0.5; extra == "extra"
Requires-Dist: netCDF4>=1.6.0; extra == "extra"
Requires-Dist: pymetalink>=6.5.3; extra == "extra"
Requires-Dist: xarray>=2023.1.0; extra == "extra"
Requires-Dist: rioxarray>=0.15.0; extra == "extra"
Dynamic: author
Dynamic: author-email
Dynamic: classifier
Dynamic: description
Dynamic: description-content-type
Dynamic: home-page
Dynamic: keywords
Dynamic: license
Dynamic: license-file
Dynamic: provides-extra
Dynamic: requires-dist
Dynamic: requires-python
Dynamic: summary
